MANIFEST.in
README.txt
setup.cfg
setup.py
docs/HISTORY.txt
docs/INSTALL.txt
docs/LICENSE.GPL
docs/LICENSE.txt
jalon/__init__.py
jalon.elasticsearch.egg-info/PKG-INFO
jalon.elasticsearch.egg-info/SOURCES.txt
jalon.elasticsearch.egg-info/dependency_links.txt
jalon.elasticsearch.egg-info/entry_points.txt
jalon.elasticsearch.egg-info/namespace_packages.txt
jalon.elasticsearch.egg-info/not-zip-safe
jalon.elasticsearch.egg-info/paster_plugins.txt
jalon.elasticsearch.egg-info/requires.txt
jalon.elasticsearch.egg-info/top_level.txt
jalon/elasticsearch/__init__.py
jalon/elasticsearch/configure.zcml
jalon/elasticsearch/skins.zcml
jalon/elasticsearch/tests.py
jalon/elasticsearch/content/__init__.py
jalon/elasticsearch/content/configure.zcml
jalon/elasticsearch/content/interfaces.py
jalon/elasticsearch/content/jalonelasticsearch.py
jalon/elasticsearch/profiles/default/componentregistry.xml
jalon/elasticsearch/profiles/default/metadata.xml
jalon/elasticsearch/profiles/default/skins.xml
jalon/elasticsearch/profiles/default/toolset.xml
jalon/elasticsearch/skins/jalon_elasticsearch/macro_formulaire_elasticsearch.pt
jalon/elasticsearch/skins/jalon_elasticsearch/saveConfigElasticsearch.py