Metadata-Version: 1.1
Name: jalon.elasticsearch
Version: 3.0
Summary: Connexion avec le moteur elasticsearch du produit Pod
Home-page: http://svn.plone.org/svn/collective/
Author: Bordonado Christophe (Université Nice Sophia Antipolis Service TICE)
Author-email: pi@unice.fr
License: GPL
Platform: UNKNOWN
Classifier: Framework :: Plone
Classifier: Programming Language :: Python
